[
  {
    "start_date": "2025-10-19T00:00:00+02:00",
    "end_date": "2025-10-19T01:00:00+02:00",
    "updated_date": "2025-10-20T00:11:19+02:00",
    "value": 5962,
    "production_type": "WIND_ONSHORE"
  },
  {
    "start_date": "2025-10-19T01:00:00+02:00",
    "end_date": "2025-10-19T02:00:00+02:00",
    "updated_date": "2025-10-20T00:11:19+02:00",
    "value": 5950,
    "production_type": "WIND_ONSHORE"
  },
  {
    "start_date": "2025-10-19T02:00:00+02:00",
    "end_date": "2025-10-19T03:00:00+02:00",
    "updated_date": "2025-10-20T00:12:38+02:00",
    "value": 5797,
    "production_type": "WIND_ONSHORE"
  },
  {
    "start_date": "2025-10-19T03:00:00+02:00",
    "end_date": "2025-10-19T04:00:00+02:00",
    "updated_date": "2025-10-20T00:12:38+02:00",
    "value": 5672,
    "production_type": "WIND_ONSHORE"
  },
  {
    "start_date": "2025-10-19T04:00:00+02:00",
    "end_date": "2025-10-19T05:00:00+02:00",
    "updated_date": "2025-10-20T00:12:38+02:00",
    "value": 5597,
    "production_type": "WIND_ONSHORE"
  },
  {
    "start_date": "2025-10-19T05:00:00+02:00",
    "end_date": "2025-10-19T06:00:00+02:00",
    "updated_date": "2025-10-20T00:12:38+02:00",
    "value": 5634,
    "production_type": "WIND_ONSHORE"
  },
  {
    "start_date": "2025-10-19T06:00:00+02:00",
    "end_date": "2025-10-19T07:00:00+02:00",
    "updated_date": "2025-10-20T00:12:38+02:00",
    "value": 5991,
    "production_type": "WIND_ONSHORE"
  },
  {
    "start_date": "2025-10-19T07:00:00+02:00",
    "end_date": "2025-10-19T08:00:00+02:00",
    "updated_date": "2025-10-20T00:12:38+02:00",
    "value": 6477,
    "production_type": "WIND_ONSHORE"
  },
  {
    "start_date": "2025-10-19T08:00:00+02:00",
    "end_date": "2025-10-19T09:00:00+02:00",
    "updated_date": "2025-10-20T00:12:38+02:00",
    "value": 6688,
    "production_type": "WIND_ONSHORE"
  },
  {
    "start_date": "2025-10-19T09:00:00+02:00",
    "end_date": "2025-10-19T10:00:00+02:00",
    "updated_date": "2025-10-20T00:12:38+02:00",
    "value": 6943,
    "production_type": "WIND_ONSHORE"
  },
  {
    "start_date": "2025-10-19T10:00:00+02:00",
    "end_date": "2025-10-19T11:00:00+02:00",
    "updated_date": "2025-10-20T00:12:38+02:00",
    "value": 6828,
    "production_type": "WIND_ONSHORE"
  },
  {
    "start_date": "2025-10-19T11:00:00+02:00",
    "end_date": "2025-10-19T12:00:00+02:00",
    "updated_date": "2025-10-20T00:12:38+02:00",
    "value": 6846,
    "production_type": "WIND_ONSHORE"
  },
  {
    "start_date": "2025-10-19T12:00:00+02:00",
    "end_date": "2025-10-19T13:00:00+02:00",
    "updated_date": "2025-10-20T00:12:38+02:00",
    "value": 6754,
    "production_type": "WIND_ONSHORE"
  },
  {
    "start_date": "2025-10-19T13:00:00+02:00",
    "end_date": "2025-10-19T14:00:00+02:00",
    "updated_date": "2025-10-20T00:12:38+02:00",
    "value": 6982,
    "production_type": "WIND_ONSHORE"
  },
  {
    "start_date": "2025-10-19T14:00:00+02:00",
    "end_date": "2025-10-19T15:00:00+02:00",
    "updated_date": "2025-10-20T00:12:38+02:00",
    "value": 6946,
    "production_type": "WIND_ONSHORE"
  },
  {
    "start_date": "2025-10-19T15:00:00+02:00",
    "end_date": "2025-10-19T16:00:00+02:00",
    "updated_date": "2025-10-20T00:12:38+02:00",
    "value": 7180,
    "production_type": "WIND_ONSHORE"
  },
  {
    "start_date": "2025-10-19T16:00:00+02:00",
    "end_date": "2025-10-19T17:00:00+02:00",
    "updated_date": "2025-10-20T00:12:38+02:00",
    "value": 8029,
    "production_type": "WIND_ONSHORE"
  },
  {
    "start_date": "2025-10-19T17:00:00+02:00",
    "end_date": "2025-10-19T18:00:00+02:00",
    "updated_date": "2025-10-20T00:12:38+02:00",
    "value": 9515,
    "production_type": "WIND_ONSHORE"
  },
  {
    "start_date": "2025-10-19T18:00:00+02:00",
    "end_date": "2025-10-19T19:00:00+02:00",
    "updated_date": "2025-10-20T00:12:38+02:00",
    "value": 10727,
    "production_type": "WIND_ONSHORE"
  },
  {
    "start_date": "2025-10-19T19:00:00+02:00",
    "end_date": "2025-10-19T20:00:00+02:00",
    "updated_date": "2025-10-20T00:12:38+02:00",
    "value": 11428,
    "production_type": "WIND_ONSHORE"
  },
  {
    "start_date": "2025-10-19T20:00:00+02:00",
    "end_date": "2025-10-19T21:00:00+02:00",
    "updated_date": "2025-10-20T00:12:38+02:00",
    "value": 11667,
    "production_type": "WIND_ONSHORE"
  },
  {
    "start_date": "2025-10-19T21:00:00+02:00",
    "end_date": "2025-10-19T22:00:00+02:00",
    "updated_date": "2025-10-20T00:12:38+02:00",
    "value": 11914,
    "production_type": "WIND_ONSHORE"
  },
  {
    "start_date": "2025-10-19T22:00:00+02:00",
    "end_date": "2025-10-19T23:00:00+02:00",
    "updated_date": "2025-10-20T00:12:38+02:00",
    "value": 11670,
    "production_type": "WIND_ONSHORE"
  },
  {
    "start_date": "2025-10-19T23:00:00+02:00",
    "end_date": "2025-10-20T00:00:00+02:00",
    "updated_date": "2025-10-20T00:12:38+02:00",
    "value": 11532,
    "production_type": "WIND_ONSHORE"
  }
]